features/__init__.py
features/landmark_detection.py
features/eye_direction/gaze_detection.py
features/eye_state/calculate_eye_rate.py
features/face_direction/direction_detector.py
features/face_direction/utils.py
features/focus/calculate_blurr.py
features/item_cut/clothing_segmentation.py
features/item_cut/u2net/base_dataset.py
features/item_cut/u2net/networks.py
features/item_cut/u2net/saving_utils.py
features/lightning/calculate_histogram.py
features/model_side/models_side.py
features/move/move_detection.py
features/pose_estimation/arm_on_waist.py
features/pose_estimation/estimation.py
features/pose_estimation/face_visibility.py
features/pose_estimation/hands.py
features/pose_estimation/legs.py
features/pose_estimation/posture.py
features/shot_size/detect_part_of_body.py
features/smiling/smile_classification.py
Holb-0.0.1.dist-info/LICENSE.txt
Holb-0.0.1.dist-info/METADATA
Holb-0.0.1.dist-info/WHEEL
Holb-0.0.1.dist-info/top_level.txt
Holb-0.0.1.dist-info/RECORD
