Metadata-Version: 2.1
Name: Holb
Version: 0.0.1
Home-page: https://github.com/Slava-git/holb.git
Author: Viacheslav Hodlevskyi
Author-email: slavagodlevsky86@gmail.com
Classifier: Programming Language :: Python :: 3
Classifier: License :: OSI Approved :: MIT License
Classifier: Operating System :: OS Independent
Requires-Python: >=3.10
License-File: LICENSE.txt
